pyfunk/__init__.py
pyfunk/collections.py
pyfunk/combinators.py
pyfunk/misc.py
pyfunk/monads/__init__.py
pyfunk/monads/base.py
pyfunk/monads/const.py
pyfunk/monads/either.py
pyfunk/monads/helpers.py
pyfunk/monads/identity.py
pyfunk/monads/io.py
pyfunk/monads/maybe.py
pyfunk/monads/reader.py
pyfunk/monads/state.py
pyfunk/monads/task.py
pyfunk/monads/writer.py
pyfunk-1.1.0.dist-info/DESCRIPTION.rst
pyfunk-1.1.0.dist-info/LICENSE.txt
pyfunk-1.1.0.dist-info/METADATA
pyfunk-1.1.0.dist-info/RECORD
pyfunk-1.1.0.dist-info/WHEEL
pyfunk-1.1.0.dist-info/metadata.json
pyfunk-1.1.0.dist-info/top_level.txt
tests/__init__.py
tests/test_collections.py
tests/test_combinators.py
tests/test_either.py
tests/test_generic_algebra.py
tests/test_helpers.py
tests/test_io.py
tests/test_maybe.py
tests/test_misc.py
tests/test_monad.py
tests/test_task.py
