Metadata-Version: 2.0
Name: pyfunk
Version: 1.1.0
Summary: UNKNOWN
Home-page: https://github.com/danceasarxx/pyfunk.git
Author: Arewa Olakunle
Author-email: arewa.olakunle@gmail.com
License: UNKNOWN
Platform: any
